ipymol/__init__.py
ipymol/compat.py
ipymol/core.py
ipymol-0.5.dist-info/DESCRIPTION.rst
ipymol-0.5.dist-info/METADATA
ipymol-0.5.dist-info/RECORD
ipymol-0.5.dist-info/WHEEL
ipymol-0.5.dist-info/metadata.json
ipymol-0.5.dist-info/top_level.txt
ipymol-0.5.dist-info/zip-safe
