Metadata-Version: 2.0
Name: ipymol
Version: 0.5
Summary: IPyMOL allows you to control PyMOL sessions via IPython.
Home-page: https://github.com/cxhernandez/ipymol
Author: Carlos Xavier Hernandez
Author-email: cxh@stanford.edu
License: MIT
Download-URL: https://github.com/cxhernandez/ipymol/tarball/master
Keywords: ipython notebook pymol protein molecular visualization
Platform: Windows
Platform: Linux
Platform: Mac OS-X
Platform: Unix
Requires-Dist: ipython
Requires-Dist: matplotlib
Requires-Dist: numpy
Requires-Dist: pillow
